klat_connector/__init__.py
klat_connector/encryptor.py
klat_connector/exceptions.py
klat_connector/klat_api.py
klat_connector/legacy_socket_adapter.py
klat_connector/logger.py
klat_connector/mach_server.py
klat_connector/mq_klat_api.py
klat_connector/api/__init__.py
klat_connector/api/klat_api_abc.py
klat_connector/api/mq_klat_api.py
klat_connector/api/sio_klat_api.py
klat_connector/utils/__init__.py
klat_connector/utils/encryptor.py
klat_connector/utils/html_utils.py
klat_connector/utils/legacy_socket_adapter.py
klat_connector/utils/mach_server.py
klat_connector/utils/sio_connection_utils.py
tests/__init__.py
tests/klat_api_tests.py
tests/units/__init__.py
tests/units/exceptions_tests.py
tests/units/utils_tests.py
klat_connector-0.7.1a1.dist-info/LICENSE.md
klat_connector-0.7.1a1.dist-info/METADATA
klat_connector-0.7.1a1.dist-info/WHEEL
klat_connector-0.7.1a1.dist-info/top_level.txt
klat_connector-0.7.1a1.dist-info/RECORD
