Metadata-Version: 2.1
Name: klat-connector
Version: 0.7.1a1
Summary: The Klat Chat API
Home-page: https://github.com/neongeckocom/klat-connector
Author: Neongecko
Author-email: developers@neon.ai
Classifier: Programming Language :: Python :: 3
Classifier: Operating System :: OS Independent
Requires-Python: >=3.6
License-File: LICENSE.md
Requires-Dist: python-socketio~=5.6
Requires-Dist: python-engineio~=4.2
Requires-Dist: websocket-client<=0.57
Requires-Dist: requests~=2.20
Requires-Dist: setuptools~=50.3
Requires-Dist: w3lib~=1.22
Requires-Dist: eventlet~=0.33
Requires-Dist: neon-mq-connector~=0.7
Requires-Dist: neon-utils~=1.0
Requires-Dist: socketIO-client==0.7.2
Provides-Extra: test
Requires-Dist: pytest; extra == "test"
Requires-Dist: pytest-timeout; extra == "test"
Requires-Dist: mock; extra == "test"
Requires-Dist: psutil; extra == "test"
Requires-Dist: neon-minerva[rmq]>=0.2.1a3,~=0.2; extra == "test"
